setup.py
SmarterMeasure.egg-info/PKG-INFO
SmarterMeasure.egg-info/SOURCES.txt
SmarterMeasure.egg-info/dependency_links.txt
SmarterMeasure.egg-info/requires.txt
SmarterMeasure.egg-info/top_level.txt
smartermeasure/__init__.py
smartermeasure/api.py
smartermeasure/errors.py