Metadata-Version: 1.1
Name: SmarterMeasure
Version: 0.1-pre
Summary: Python client for the SmarterMeasure REST API
Home-page: https://github.com/Trii/smartermeasure-python
Author: Joshua Johnston
Author-email: johnston.joshua@gmail.com
License: PSF
Keywords: SmarterMeasure API
Platform: UNKNOWN
Classifier: Development Status :: 3 - Alpha
